Metadata-Version: 1.1
Name: django-taggit-serializer
Version: 0.1.5
Summary: The Django Taggit serializer for tDjango REST Framework
Home-page: https://github.com/glemmaPaul/django-taggit-serializer
Author: Paul Oostenrijk
Author-email: paul@glemma.nl
License: BSD
Keywords: django-taggit-serializer
Platform: UNKNOWN
Classifier: Development Status :: 2 - Pre-Alpha
Classifier: Framework :: Django
Classifier: Intended Audience :: Developers
Classifier: License :: OSI Approved :: BSD License
Classifier: Natural Language :: English
Classifier: Programming Language :: Python :: 2
Classifier: Programming Language :: Python :: 2.6
Classifier: Programming Language :: Python :: 2.7
Classifier: Programming Language :: Python :: 3
Classifier: Programming Language :: Python :: 3.3
